salix_containers/__init__.py
salix_containers/caselessmapping.py
salix_containers/casttypes.py
salix_containers/empty.py
salix_containers/tests/__init__.py
salix_containers/tests/test_caselessmappings.py
salix_containers/tests/test_casttypes.py
salix_containers/tests/test_empty.py
salix_containers-0.5.0.dist-info/METADATA
salix_containers-0.5.0.dist-info/WHEEL
salix_containers-0.5.0.dist-info/RECORD
